rootchecker/__init__.py
rootchecker/rootchecker.py
rootchecker-0.3.0.dist-info/LICENSE
rootchecker-0.3.0.dist-info/METADATA
rootchecker-0.3.0.dist-info/WHEEL
rootchecker-0.3.0.dist-info/top_level.txt
rootchecker-0.3.0.dist-info/RECORD
