Metadata-Version: 2.1
Name: rootchecker
Version: 0.3.0
Summary: Simple rootchecker for Android that written in python
Author: yakupaslantas
License-File: LICENSE
